odoo/addons/partner_postal_address/README.rst
odoo/addons/partner_postal_address/__init__.py
odoo/addons/partner_postal_address/__manifest__.py
odoo/addons/partner_postal_address/i18n/fr.po
odoo/addons/partner_postal_address/i18n/partner_postal_address.pot
odoo/addons/partner_postal_address/models/__init__.py
odoo/addons/partner_postal_address/models/res_partner.py
odoo/addons/partner_postal_address/readme/CONTRIBUTORS.rst
odoo/addons/partner_postal_address/readme/CREDITS.rst
odoo/addons/partner_postal_address/readme/DESCRIPTION.rst
odoo/addons/partner_postal_address/readme/USAGE.rst
odoo/addons/partner_postal_address/static/description/icon.png
odoo/addons/partner_postal_address/static/description/index.html
odoo12_addon_partner_postal_address-12.0.1.0.0.99.dev4.dist-info/METADATA
odoo12_addon_partner_postal_address-12.0.1.0.0.99.dev4.dist-info/WHEEL
odoo12_addon_partner_postal_address-12.0.1.0.0.99.dev4.dist-info/top_level.txt
odoo12_addon_partner_postal_address-12.0.1.0.0.99.dev4.dist-info/RECORD
